{
    "ROOT": [
        {
            "NAME": "SNR_0_0_0",
            "CHIP": "0",
            "DELAY": "0"
        },
        {
            "NAME": "FILE_0_0_0",
            "CHIP": "0",
            "DELAY": "0"
        },
        {
            "NAME": "POOL_0_0_0",
            "CHIP": "0",
            "DELAY": "0"
        }
    ],
    "FILE_0_0_0": {
        "MOD": "FILE",
        "DEV": "0",
        "CHN": "0",
        "CHIP_ID": "0",
        "PRELOAD": "0",
        "IN_0": {
            "PORT": "0",
            "PREV": "VENC_0_0_0:OUT_0",
            "HEAD": "0",
            "FRAME_CNT_LIMIT": "0",
            "FILE_WRITE_PATH": "./record_default",
            "FPS": "30",
            "BIND_PARAM": "0",
            "BIND_TYPE": "1"
        },
        "IN_1": {
            "PORT": "1",
            "PREV": "VENC_8_0_0:OUT_0",
            "HEAD": "0",
            "FRAME_CNT_LIMIT": "0",
            "FILE_WRITE_PATH": "./capture_default",
            "FPS": "1",
            "BIND_PARAM": "0",
            "BIND_TYPE": "1"
        },
        "IN_2": {
            "PORT": "2",
            "PREV": "VENC_8_1_0:OUT_0",
            "HEAD": "0",
            "FRAME_CNT_LIMIT": "0",
            "FILE_WRITE_PATH": "./capture_thumbnail",
            "FPS": "1",
            "BIND_PARAM": "0",
            "BIND_TYPE": "1"
        },
        "IN_3": {
            "PORT": "3",
            "PREV": "VENC_8_2_0:OUT_0",
            "HEAD": "0",
            "FRAME_CNT_LIMIT": "0",
            "FILE_WRITE_PATH": "./record_thumbnail",
            "FPS": "1",
            "BIND_PARAM": "0",
            "BIND_TYPE": "1"
        },
        "IN_CNT": "4",
        "OUT_CNT": "0",
        "POS_X": "1120",
        "POS_Y": "343"
    },
    "VENC_0_0_0": {
        "MOD": "VENC",
        "DEV": "0",
        "CHN": "0",
        "CHIP_ID": "0",
        "PRELOAD": "0",
        "IN_0": {
            "PORT": "0",
            "PREV": "SCL_1_0_0:OUT_0",
            "FPS": "30",
            "BIND_PARAM": "0",
            "BIND_TYPE": "16"
        },
        "OUT_0": {
            "PORT": "0",
            "DEPTH_EN": "0",
            "EXT_EN": "0",
            "FPS": "30",
            "USER_FRC_EN": "0",
            "BW_INFO": "0",
            "BW_PARAM": null,
            "DEPTH_PARAM": null,
            "EXT_PARAM": null
        },
        "IN_CNT": "1",
        "OUT_CNT": "1",
        "POS_X": "916",
        "POS_Y": "279",
        "BW_INFO": "0",
        "DEBREATH_ENABLE": "0",
        "EN_FPS": "30",
        "EN_TYPE": "h265",
        "LTR_EN": "0",
        "MAX_STREAM_CNT": "30",
        "STREAM_CNT_EN": "0",
        "MAX_STREAM_H": "1512",
        "MAX_STREAM_W": "2016",
        "MULTI_SLICE": "0",
        "RC_MODE": "cbr",
        "ROI_NUM": "0",
        "SLICE_ROW_CNT": "0",
        "STREAM_H": "1512",
        "STREAM_W": "2016",
        "YUV_EN": "0",
        "BW_PARAM": null,
        "DEBREATH_PARAM": null,
        "LTR_PARAM": null,
        "RC_MODE_PARAM": {
            "BIT_RATE": "4000",
            "GOP": "60"
        },
        "YUV_PARAM": null
    },
    "VENC_8_2_0": {
        "MOD": "VENC",
        "DEV": "8",
        "CHN": "2",
        "CHIP_ID": "0",
        "PRELOAD": "0",
        "IN_0": {
            "PORT": "0",
            "PREV": "SCL_1_0_0:OUT_1",
            "FPS": "1",
            "BIND_PARAM": "0",
            "BIND_TYPE": "1"
        },
        "OUT_0": {
            "PORT": "0",
            "DEPTH_EN": "0",
            "EXT_EN": "0",
            "FPS": "1",
            "USER_FRC_EN": "0",
            "BW_INFO": "0",
            "BW_PARAM": null,
            "DEPTH_PARAM": null,
            "EXT_PARAM": null
        },
        "IN_CNT": "1",
        "OUT_CNT": "1",
        "POS_X": "916",
        "POS_Y": "329",
        "BW_INFO": "0",
        "DEBREATH_ENABLE": "0",
        "EN_FPS": "1",
        "EN_TYPE": "jpeg",
        "LTR_EN": "0",
        "MAX_STREAM_CNT": "1",
        "STREAM_CNT_EN": "0",
        "MAX_STREAM_H": "720",
        "MAX_STREAM_W": "1280",
        "MULTI_SLICE": "0",
        "RC_MODE": "fixqp",
        "ROI_NUM": "0",
        "SLICE_ROW_CNT": "5",
        "STREAM_H": "720",
        "STREAM_W": "1280",
        "YUV_EN": "0",
        "BW_PARAM": null,
        "DEBREATH_PARAM": null,
        "LTR_PARAM": null,
        "RC_MODE_PARAM": {
            "BIT_RATE": "100000",
            "GOP": "50",
            "IQP": "40",
            "PQP": "40",
            "QFACTOR": "70"
        },
        "YUV_PARAM": null
    },
    "SCL_1_0_0": {
        "MOD": "SCL",
        "DEV": "1",
        "CHN": "0",
        "CHIP_ID": "0",
        "PRELOAD": "0",
        "IN_0": {
            "PORT": "0",
            "PREV": "LDC_0_0_0:OUT_0",
            "FPS": "30",
            "BIND_PARAM": "0",
            "BIND_TYPE": "1",
            "VID_CROP_H": "0",
            "VID_CROP_W": "0",
            "VID_CROP_X": "0",
            "VID_CROP_Y": "0"
        },
        "OUT_0": {
            "PORT": "0",
            "DEPTH_EN": "0",
            "EXT_EN": "0",
            "FPS": "30",
            "USER_FRC_EN": "0",
            "IS_FLIP": "0",
            "IS_MIRROR": "0",
            "BW_INFO": "0",
            "OUT_FMT": "nv12",
            "COMPRESS_MODE": "0",
            "VID_CROP_H": "0",
            "VID_CROP_W": "0",
            "VID_CROP_X": "0",
            "VID_CROP_Y": "0",
            "VID_H": "1512",
            "OUT_TYPE": "raw",
            "VID_W": "2016",
            "BW_PARAM": null,
            "DEPTH_PARAM": null,
            "EXT_PARAM": null
        },
        "OUT_1": {
            "PORT": "2",
            "DEPTH_EN": "0",
            "EXT_EN": "0",
            "FPS": "1",
            "USER_FRC_EN": "0",
            "IS_FLIP": "0",
            "IS_MIRROR": "0",
            "BW_INFO": "0",
            "OUT_FMT": "nv12",
            "COMPRESS_MODE": "0",
            "VID_CROP_H": "0",
            "VID_CROP_W": "0",
            "VID_CROP_X": "0",
            "VID_CROP_Y": "0",
            "VID_H": "720",
            "OUT_TYPE": "raw",
            "VID_W": "1280",
            "BW_PARAM": null,
            "DEPTH_PARAM": null,
            "EXT_PARAM": null
        },
        "IN_CNT": "1",
        "OUT_CNT": "2",
        "POS_X": "713",
        "POS_Y": "268",
        "PORT_MODE": "0x7",
        "ROT": "0"
    },
    "LDC_0_0_0": {
        "MOD": "LDC",
        "DEV": "0",
        "CHN": "0",
        "CHIP_ID": "0",
        "PRELOAD": "0",
        "IN_0": {
            "PORT": "0",
            "PREV": "AESTABLE_0_0_0:OUT_0",
            "FPS": "30",
            "VID_H": "2160",
            "VID_W": "3840",
            "BIND_PARAM": "0",
            "BIND_TYPE": "0x1"
        },
        "OUT_0": {
            "PORT": "0",
            "OUT_TYPE": "raw",
            "VID_H": "2160",
            "OUT_FMT": "nv12",
            "VID_W": "3840",
            "DEPTH_EN": "0",
            "EXT_EN": "0",
            "FPS": "30",
            "USER_FRC_EN": "0",
            "DEPTH_PARAM": null,
            "EXT_PARAM": null
        },
        "IN_CNT": "1",
        "OUT_CNT": "1",
        "POS_X": "665",
        "POS_Y": "225",
        "BW_INFO": "0",
        "WORK_MODE": "dis_ldc",
        "BW_PARAM": null,
        "WORK_MODE_PARAM": {
            "BGCOLOR": "0xff0000",
            "ENABLE_BGCOLOR": "1",
            "REGION_MAX": "1",
            "REGION_NUM": "1",
            "CALIB_PATH": "./resource/CalibPoly_new.bin",
            "CENTER_X_OFFSET": "0",
            "CENTER_Y_OFFSET": "0",
            "FISHEYE_RADIUS": "585",
            "MOUNT_MODE": "2",
            "REGION_0": {
                "GRID": "./LDC_map_case_1920_1088/Grid.bin",
                "MAP_X": "./LDC_map_case_1920_1088/mapX.bin",
                "MAP_Y": "./LDC_map_case_1920_1088/mapY.bin",
                "ROT": "0",
                "CROP_MODE": "0",
                "DISTORTION_RATIO": "0",
                "FOCAL_RATIO": "0",
                "IN_RADIUS": "0",
                "OUT_RADIUS": "550",
                "OUT_RECT_HEIGHT": "2160",
                "OUT_RECT_WIDTH": "3840",
                "OUT_RECT_X": "0",
                "OUT_RECT_Y": "0",
                "OUT_ROT": "0",
                "PAN": "0",
                "REGION_MODE": "5",
                "TILT": "10",
                "ZOOM_H": "360",
                "ZOOM_V": "550"
            },
            "CROP_RATIO": "50",
            "FOCAL_LEN_X": "370370",
            "FOCAL_LEN_Y": "370370",
            "DIS_MODE": "3",
            "MOTION_LEVEL": "1",
            "ROTATION_MATRIX": "-1,0,0,0,-1,0,0,0,1",
            "SCENE_TYPE": "0",
            "USER_SLICE_NUM": "6"
        }
    },
    "AESTABLE_0_0_0": {
        "MOD": "AESTABLE",
        "DEV": "0",
        "CHN": "0",
        "CHIP_ID": "0",
        "PRELOAD": "0",
        "IN_0": {
            "PORT": "0",
            "PREV": "PASS_0_0_0:OUT_0",
            "FPS": "30",
            "BIND_PARAM": "0",
            "BIND_TYPE": "0x1"
        },
        "OUT_0": {
            "PORT": "0",
            "DEPTH_EN": "0",
            "EXT_EN": "0",
            "FPS": "30",
            "USER_FRC_EN": "0",
            "DEPTH_PARAM": null,
            "EXT_PARAM": null
        },
        "IN_CNT": "1",
        "OUT_CNT": "1",
        "POS_X": "507",
        "POS_Y": "257",
        "DEBUG_MODE": "0",
        "RUN_MODE": "record",
        "START_MODE": "auto",
        "RUN_MODE_PARAM": {
            "STABLE_COUNT": "1"
        }
    },
    "PASS_0_0_0": {
        "MOD": "PASS",
        "DEV": "0",
        "CHN": "0",
        "CHIP_ID": "0",
        "PRELOAD": "0",
        "OUT_0": {
            "PORT": "0",
            "HEAD": "ISP_0_0_0",
            "HEAD_OUT_ID": "1",
            "DEPTH_EN": "0",
            "EXT_EN": "0",
            "FPS": "30",
            "USER_FRC_EN": "0",
            "ROOT_CNT": "2",
            "DEPTH_PARAM": null,
            "EXT_PARAM": null,
            "ROOT_0": {
                "SEC_NAME": "ISP_0_0_0"
            },
            "ROOT_1": {
                "SEC_NAME": "IQ_0_0_0"
            }
        },
        "OUT_1": {
            "PORT": "1",
            "HEAD": "ISP_0_1_0",
            "HEAD_OUT_ID": "1",
            "DEPTH_EN": "0",
            "EXT_EN": "0",
            "FPS": "15",
            "USER_FRC_EN": "0",
            "ROOT_CNT": "2",
            "DEPTH_PARAM": null,
            "EXT_PARAM": null,
            "ROOT_0": {
                "SEC_NAME": "ISP_0_1_0"
            },
            "ROOT_1": {
                "SEC_NAME": "IQ_0_1_0"
            }
        },
        "IN_0": {
            "PORT": "0",
            "PREV": "VIF_0_0_0:OUT_0",
            "FPS": "30",
            "BIND_PARAM": "0",
            "BIND_TYPE": "0x1",
            "TAIL": "ISP_0_0_0",
            "TAIL_IN_ID": "0"
        },
        "IN_1": {
            "PORT": "1",
            "PREV": "VIF_0_0_0:OUT_0",
            "FPS": "15",
            "BIND_PARAM": "0",
            "BIND_TYPE": "0x1",
            "TAIL": "ISP_0_1_0",
            "TAIL_IN_ID": "0"
        },
        "IN_CNT": "2",
        "OUT_CNT": "2",
        "POS_X": "293",
        "POS_Y": "306"
    },
    "VIF_0_0_0": {
        "MOD": "VIF",
        "DEV": "0",
        "CHN": "0",
        "CHIP_ID": "0",
        "PRELOAD": "0",
        "OUT_0": {
            "PORT": "0",
            "DEPTH_EN": "1",
            "EXT_EN": "0",
            "FPS": "15",
            "USER_FRC_EN": "0",
            "OUT_FMT": "nv12",
            "COMPRESS_MODE": "0",
            "VID_CROP_H": "0",
            "VID_CROP_W": "0",
            "VID_CROP_X": "0",
            "VID_CROP_Y": "0",
            "VID_H": "0",
            "OUT_TYPE": "raw",
            "USE_SNR_FMT": "1",
            "VID_W": "0",
            "BAYER_PARAM": null,
            "DEPTH_PARAM": {
                "DEPTH_TOTAL": "3",
                "DEPTH_USER": "0"
            },
            "EXT_PARAM": null
        },
        "IN_CNT": "0",
        "OUT_CNT": "1",
        "POS_X": "99",
        "POS_Y": "297",
        "HDR_EXPOSURE_MASK": "0",
        "HDR_TYPE": "0",
        "SNR_ID": "0",
        "GROUP_STITCH_MASK": "0",
        "WORK_MOD": "0"
    },
    "VENC_8_0_0": {
        "MOD": "VENC",
        "DEV": "8",
        "CHN": "0",
        "CHIP_ID": "0",
        "PRELOAD": "0",
        "IN_0": {
            "PORT": "0",
            "PREV": "SCL_1_1_0:OUT_0",
            "FPS": "1",
            "BIND_PARAM": "0",
            "BIND_TYPE": "1"
        },
        "OUT_0": {
            "PORT": "0",
            "DEPTH_EN": "0",
            "EXT_EN": "0",
            "FPS": "1",
            "USER_FRC_EN": "0",
            "BW_INFO": "0",
            "BW_PARAM": null,
            "DEPTH_PARAM": null,
            "EXT_PARAM": null
        },
        "IN_CNT": "1",
        "OUT_CNT": "1",
        "POS_X": "913",
        "POS_Y": "409",
        "BW_INFO": "0",
        "DEBREATH_ENABLE": "0",
        "EN_FPS": "1",
        "EN_TYPE": "jpeg",
        "LTR_EN": "0",
        "MAX_STREAM_CNT": "1",
        "STREAM_CNT_EN": "0",
        "MAX_STREAM_H": "3024",
        "MAX_STREAM_W": "4032",
        "MULTI_SLICE": "0",
        "RC_MODE": "fixqp",
        "ROI_NUM": "0",
        "SLICE_ROW_CNT": "5",
        "STREAM_H": "3024",
        "STREAM_W": "4032",
        "YUV_EN": "0",
        "BW_PARAM": null,
        "DEBREATH_PARAM": null,
        "LTR_PARAM": null,
        "RC_MODE_PARAM": {
            "BIT_RATE": "100000",
            "GOP": "50",
            "IQP": "40",
            "PQP": "40",
            "QFACTOR": "70"
        },
        "YUV_PARAM": null
    },
    "VENC_8_1_0": {
        "MOD": "VENC",
        "DEV": "8",
        "CHN": "1",
        "CHIP_ID": "0",
        "PRELOAD": "0",
        "IN_0": {
            "PORT": "0",
            "PREV": "SCL_1_1_0:OUT_1",
            "FPS": "1",
            "BIND_PARAM": "0",
            "BIND_TYPE": "1"
        },
        "OUT_0": {
            "PORT": "0",
            "DEPTH_EN": "0",
            "EXT_EN": "0",
            "FPS": "1",
            "USER_FRC_EN": "0",
            "BW_INFO": "0",
            "BW_PARAM": null,
            "DEPTH_PARAM": null,
            "EXT_PARAM": null
        },
        "IN_CNT": "1",
        "OUT_CNT": "1",
        "POS_X": "913",
        "POS_Y": "459",
        "BW_INFO": "0",
        "DEBREATH_ENABLE": "0",
        "EN_FPS": "1",
        "EN_TYPE": "jpeg",
        "LTR_EN": "0",
        "MAX_STREAM_CNT": "1",
        "STREAM_CNT_EN": "0",
        "MAX_STREAM_H": "720",
        "MAX_STREAM_W": "1280",
        "MULTI_SLICE": "0",
        "RC_MODE": "fixqp",
        "ROI_NUM": "0",
        "SLICE_ROW_CNT": "5",
        "STREAM_H": "720",
        "STREAM_W": "1280",
        "YUV_EN": "0",
        "BW_PARAM": null,
        "DEBREATH_PARAM": null,
        "LTR_PARAM": null,
        "RC_MODE_PARAM": {
            "BIT_RATE": "100000",
            "GOP": "50",
            "IQP": "40",
            "PQP": "40",
            "QFACTOR": "70"
        },
        "YUV_PARAM": null
    },
    "SCL_1_1_0": {
        "MOD": "SCL",
        "DEV": "1",
        "CHN": "1",
        "CHIP_ID": "0",
        "PRELOAD": "0",
        "IN_0": {
            "PORT": "0",
            "PREV": "LDC_0_1_0:OUT_0",
            "FPS": "1",
            "BIND_PARAM": "0",
            "BIND_TYPE": "1",
            "VID_CROP_H": "0",
            "VID_CROP_W": "0",
            "VID_CROP_X": "0",
            "VID_CROP_Y": "0"
        },
        "OUT_0": {
            "PORT": "1",
            "DEPTH_EN": "0",
            "EXT_EN": "0",
            "FPS": "1",
            "USER_FRC_EN": "0",
            "IS_FLIP": "0",
            "IS_MIRROR": "0",
            "BW_INFO": "0",
            "OUT_FMT": "yuyv",
            "COMPRESS_MODE": "0",
            "VID_CROP_H": "0",
            "VID_CROP_W": "0",
            "VID_CROP_X": "0",
            "VID_CROP_Y": "0",
            "VID_H": "3024",
            "OUT_TYPE": "raw",
            "VID_W": "4032",
            "BW_PARAM": null,
            "DEPTH_PARAM": null,
            "EXT_PARAM": null
        },
        "OUT_1": {
            "PORT": "2",
            "DEPTH_EN": "0",
            "EXT_EN": "0",
            "FPS": "1",
            "USER_FRC_EN": "0",
            "IS_FLIP": "0",
            "IS_MIRROR": "0",
            "BW_INFO": "0",
            "OUT_FMT": "yuyv",
            "COMPRESS_MODE": "0",
            "VID_CROP_H": "0",
            "VID_CROP_W": "0",
            "VID_CROP_X": "0",
            "VID_CROP_Y": "0",
            "VID_H": "720",
            "OUT_TYPE": "raw",
            "VID_W": "1280",
            "BW_PARAM": null,
            "DEPTH_PARAM": null,
            "EXT_PARAM": null
        },
        "IN_CNT": "1",
        "OUT_CNT": "2",
        "POS_X": "713",
        "POS_Y": "397",
        "PORT_MODE": "0x7",
        "ROT": "0"
    },
    "LDC_0_1_0": {
        "MOD": "LDC",
        "DEV": "0",
        "CHN": "1",
        "CHIP_ID": "0",
        "PRELOAD": "7274580",
        "IN_0": {
            "PORT": "0",
            "PREV": "AESTABLE_0_1_0:OUT_0",
            "FPS": "30",
            "VID_H": "2160",
            "VID_W": "3840",
            "BIND_PARAM": "0",
            "BIND_TYPE": "0x1"
        },
        "OUT_0": {
            "PORT": "0",
            "OUT_TYPE": "raw",
            "VID_H": "2160",
            "OUT_FMT": "yuyv",
            "VID_W": "3840",
            "DEPTH_EN": "0",
            "EXT_EN": "0",
            "FPS": "30",
            "USER_FRC_EN": "0",
            "DEPTH_PARAM": null,
            "EXT_PARAM": null
        },
        "IN_CNT": "1",
        "OUT_CNT": "1",
        "POS_X": "662",
        "POS_Y": "355",
        "BW_INFO": "0",
        "WORK_MODE": "ldc",
        "BW_PARAM": null,
        "WORK_MODE_PARAM": {
            "BGCOLOR": "0xff0000",
            "ENABLE_BGCOLOR": "1",
            "REGION_MAX": "1",
            "REGION_NUM": "1",
            "CALIB_PATH": "./resource/CalibPoly_new.bin",
            "CENTER_X_OFFSET": "0",
            "CENTER_Y_OFFSET": "0",
            "FISHEYE_RADIUS": "585",
            "MOUNT_MODE": "2",
            "REGION_0": {
                "GRID": "./LDC_map_case_1920_1088/Grid.bin",
                "MAP_X": "./LDC_map_case_1920_1088/mapX.bin",
                "MAP_Y": "./LDC_map_case_1920_1088/mapY.bin",
                "ROT": "0",
                "CROP_MODE": "0",
                "DISTORTION_RATIO": "0",
                "FOCAL_RATIO": "0",
                "IN_RADIUS": "0",
                "OUT_RADIUS": "550",
                "OUT_RECT_HEIGHT": "2160",
                "OUT_RECT_WIDTH": "3840",
                "OUT_RECT_X": "0",
                "OUT_RECT_Y": "0",
                "OUT_ROT": "0",
                "PAN": "0",
                "REGION_MODE": "5",
                "TILT": "10",
                "ZOOM_H": "360",
                "ZOOM_V": "550"
            }
        }
    },
    "AESTABLE_0_1_0": {
        "MOD": "AESTABLE",
        "DEV": "0",
        "CHN": "1",
        "CHIP_ID": "0",
        "PRELOAD": "0",
        "IN_0": {
            "PORT": "0",
            "PREV": "PASS_0_0_0:OUT_1",
            "FPS": "1",
            "BIND_PARAM": "0",
            "BIND_TYPE": "1"
        },
        "OUT_0": {
            "PORT": "0",
            "DEPTH_EN": "0",
            "EXT_EN": "0",
            "FPS": "1",
            "USER_FRC_EN": "0",
            "DEPTH_PARAM": null,
            "EXT_PARAM": null
        },
        "IN_CNT": "1",
        "OUT_CNT": "1",
        "POS_X": "515",
        "POS_Y": "385",
        "DEBUG_MODE": "0",
        "RUN_MODE": "shot",
        "START_MODE": "auto",
        "RUN_MODE_PARAM": {
            "CAPTURE_COUNT": "1",
            "STABLE_COUNT": "0",
            "USING_LOW_POWER": "0"
        }
    },
    "POOL_0_0_0": {
        "MOD": "POOL",
        "DEV": "0",
        "CHN": "0",
        "CHIP_ID": "0",
        "PRELOAD": "0",
        "IN_CNT": "0",
        "OUT_CNT": "0",
        "POS_X": "894",
        "POS_Y": "219",
        "DEV_ID": "1",
        "DEV_MOD": "34",
        "VID_H": "1512",
        "RING_LINE": "1514",
        "VID_W": "2016"
    },
    "ISP_0_1_0": {
        "MOD": "ISP",
        "DEV": "0",
        "CHN": "1",
        "CHIP_ID": "0",
        "PRELOAD": "0",
        "IN_0": {
            "PORT": "0",
            "PREV": "",
            "FPS": "15",
            "VID_CROP_H": "0",
            "VID_CROP_W": "0",
            "VID_CROP_X": "0",
            "VID_CROP_Y": "0",
            "BIND_PARAM": "0",
            "BIND_TYPE": "1"
        },
        "OUT_0": {
            "PORT": "1",
            "BUF_LAYOUT": "0",
            "OUT_FMT": "nv12",
            "COMPRESS_MODE": "0",
            "VID_CROP_H": "0",
            "VID_CROP_W": "0",
            "VID_CROP_X": "0",
            "VID_CROP_Y": "0",
            "OUT_TYPE": "raw",
            "DEPTH_EN": "1",
            "EXT_EN": "0",
            "FPS": "15",
            "USER_FRC_EN": "0",
            "DEPTH_PARAM": {
                "DEPTH_TOTAL": "4",
                "DEPTH_USER": "2"
            },
            "EXT_PARAM": null
        },
        "IN_CNT": "1",
        "OUT_CNT": "1",
        "POS_X": "295",
        "POS_Y": "376",
        "SYNC_3A_TYPE": "0",
        "3DNR_LV": "0",
        "IQ_API_FILE": "/config/iqfile/imx681_12M15fps_demo_v01.bin",
        "CUST_IQ_EN": "0",
        "IS_FLIP": "0",
        "HDR_EXPOSURE_MASK": "0",
        "HDR_FUSION_TYPE": "0",
        "HDR_TYPE": "0",
        "ISP_LDC_EN": "0",
        "IS_MIRROR": "0",
        "MUTI_CHN_EN": "1",
        "OVER_LAP_EN": "1",
        "ROT": "0",
        "SNR_MASK": "1",
        "SNR_MASK_NUM": "0",
        "STITCH_MASK": "1",
        "SUB_CHN_IQ_EN": "0",
        "ZOOM_EN": "0",
        "CUST_IQ_PARAM": null,
        "ISP_LDC_PARAM": null,
        "OVER_LAP_PARAM": {
            "OVER_LAP_TYPE": "128"
        },
        "SUB_CHN_IQ_PARAM": null,
        "ZOOM_PARAM": null
    },
    "IQ_0_1_0": {
        "MOD": "IQ",
        "DEV": "0",
        "CHN": "1",
        "CHIP_ID": "0",
        "PRELOAD": "0",
        "IN_CNT": "0",
        "OUT_CNT": "0",
        "POS_X": "294",
        "POS_Y": "419",
        "CALI_CFG_CNT": "1",
        "CALI_CFG_0": {
            "IQ_CALI_FILE": "/config/iqfile/imx681_api.bin",
            "IQ_CALI_ITEM": "ne"
        },
        "CUS3A": "0",
        "CUS3A_AE": "0",
        "CUS3A_AF": "0",
        "CUS3A_AWB": "0",
        "CUS3A_BLOCK": "1",
        "CUS3A_TYPE": "cus",
        "DO_OPEN_IQ_SRV": "1",
        "IQ_USR_KEY": "1234"
    },
    "ISP_0_0_0": {
        "MOD": "ISP",
        "DEV": "0",
        "CHN": "0",
        "CHIP_ID": "0",
        "PRELOAD": "0",
        "IN_0": {
            "PORT": "0",
            "PREV": "",
            "FPS": "30",
            "VID_CROP_H": "0",
            "VID_CROP_W": "0",
            "VID_CROP_X": "0",
            "VID_CROP_Y": "0",
            "BIND_PARAM": "0",
            "BIND_TYPE": "1"
        },
        "OUT_0": {
            "PORT": "1",
            "BUF_LAYOUT": "0",
            "OUT_FMT": "nv12",
            "COMPRESS_MODE": "0",
            "VID_CROP_H": "0",
            "VID_CROP_W": "0",
            "VID_CROP_X": "0",
            "VID_CROP_Y": "0",
            "OUT_TYPE": "raw",
            "DEPTH_EN": "0",
            "EXT_EN": "0",
            "FPS": "30",
            "USER_FRC_EN": "0",
            "DEPTH_PARAM": null,
            "EXT_PARAM": null
        },
        "IN_CNT": "1",
        "OUT_CNT": "1",
        "POS_X": "294",
        "POS_Y": "235",
        "SYNC_3A_TYPE": "0",
        "3DNR_LV": "0",
        "IQ_API_FILE": "/config/iqfile/imx681_1512p30_demo_v39_NE.bin",
        "CUST_IQ_EN": "0",
        "IS_FLIP": "0",
        "HDR_EXPOSURE_MASK": "0",
        "HDR_FUSION_TYPE": "0",
        "HDR_TYPE": "0",
        "ISP_LDC_EN": "0",
        "IS_MIRROR": "0",
        "MUTI_CHN_EN": "0",
        "OVER_LAP_EN": "0",
        "ROT": "0",
        "SNR_MASK": "1",
        "SNR_MASK_NUM": "0",
        "STITCH_MASK": "1",
        "SUB_CHN_IQ_EN": "0",
        "ZOOM_EN": "0",
        "CUST_IQ_PARAM": null,
        "ISP_LDC_PARAM": null,
        "OVER_LAP_PARAM": null,
        "SUB_CHN_IQ_PARAM": null,
        "ZOOM_PARAM": null
    },
    "IQ_0_0_0": {
        "MOD": "IQ",
        "DEV": "0",
        "CHN": "0",
        "CHIP_ID": "0",
        "PRELOAD": "0",
        "IN_CNT": "0",
        "OUT_CNT": "0",
        "POS_X": "292",
        "POS_Y": "192",
        "CALI_CFG_CNT": "1",
        "CALI_CFG_0": {
            "IQ_CALI_FILE": "/config/iqfile/imx681_api.bin",
            "IQ_CALI_ITEM": "ne"
        },
        "CUS3A": "0",
        "CUS3A_AE": "0",
        "CUS3A_AF": "0",
        "CUS3A_AWB": "0",
        "CUS3A_BLOCK": "1",
        "CUS3A_TYPE": "cus",
        "DO_OPEN_IQ_SRV": "1",
        "IQ_USR_KEY": "1234"
    },
    "SNR_0_0_0": {
        "MOD": "SNR",
        "DEV": "0",
        "CHN": "0",
        "CHIP_ID": "0",
        "PRELOAD": "0",
        "IN_CNT": "0",
        "OUT_CNT": "0",
        "POS_X": "97",
        "POS_Y": "259",
        "SNR_FLIP": "0",
        "SNR_FPS": "15",
        "HDR_TYPE": "0",
        "SNR_ID": "0",
        "SNR_MIRROR": "0",
        "SNR_RES": "0"
    }
}
